02_Basic_Combinational/014_Demux/Demux_1X16/demux_1X16.v
module demux_1X2(
input y,s3,
output i0,i1);

 assign i0=y&~s3;
 assign i1=y&s3;

endmodule 

module demux_1X8(
input y,s2,s1,s0,
output i0,i1,i2,i3,i4,i5,i6,i7);

assign i0=y&~s2&~s1&~s0;
assign i1=y&~s2&~s1&s0;
assign i2=y&~s2&s1&~s0;
assign i3=y&~s2&s1&s0;
assign i4=y&s2&~s1&~s0;
assign i5=y&s2&~s1&s0;
assign i6=y&s2&s1&~s0;
assign i7=y&s2&s1&s0;

endmodule 

module demux_1X16(
input y,s3,s2,s1,s0,
output i0,i1,i2,i3,i4,i5,i6,i7,i8,i9,i10,i11,i12,i13,i14,i15);
     wire y1,y2;
  demux_1X2 dm1(.y(y),.s3(s3),.i0(y1),.i1(y2));
  demux_1X8 dm2(.y(y1),.s2(s2),.s1(s1),.s0(s0),.i0(i0),.i1(i1),.i2(i2),.i3(i3),.i4(i4),.i5(i5),.i6(i6),.i7(i7));
  demux_1X8 dm3(.y(y2),.s2(s2),.s1(s1),.s0(s0),.i0(i8),.i1(i9),.i2(i10),.i3(i11),.i4(i12),.i5(i13),.i6(i14),.i7(i15));

endmodule

02_Basic_Combinational/014_Demux/Demux_1X16/demux_1X16_tb.v
module demux_1X16_tb();
 reg y,s3,s2,s1,s0;
 wire i0,i1,i2,i3,i4,i5,i6,i7,i8,i9,i10,i11,i12,i13,i14,i15;

demux_1X16 dut(.i0(i0),.i1(i1),.i2(i2),.i3(i3),.i4(i4),.i5(i5),.i6(i6),.i7(i7),.i8(i8),.i9(i9),.i10(i10),.i11(i11),.i12(i12),.i13(i13),.i14(i14),.i15(i15),.s0(s0),.s1(s1),.s2(s2),.s3(s3),.y(y));

  initial begin 

  $monitor("TIME=%0t  || I0=%B I1=%B I2=%B I3=%B I4=%B I5=%B I6=%B I7=%B I8=%B I9=%B I10=%B I11=%B I12=%B I13=%B I14=%B I15=%B ||S3=%B S2=%B S1=%B S0=%b  ||  Y=%B",$time,i0,i1,i2,i3,i4,i5,i6,i7,i8,i9,i10,i11,i12,i13,i14,i15,s3,s2,s1,s0,y);
  $dumpfile("waveform.vcd");
  $dumpvars(0,demux_1X16_tb);

	y=1;
 
        s3=0;s2=0;s1=0;s0=0;#10;
        s0=1;#10;
	s1=1;s0=0;#10;
	s0=1;#10;
	s2=1;s1=0;s0=0;#10;
	s0=1;#10;
	s1=1;s0=0;#10;
	s0=1;#10;
	s3=1;s2=0;s1=0;s0=0;#10;
	s0=1;#10;
	s1=1;s0=0;#10;
	s0=1;#10;
	s2=1;s1=0;s0=0;#10;
	s0=1;#10;
	s1=1;s0=0;#10;
	s0=1;#10;
 
  $finish;
end
endmodule

02_Basic_Combinational/014_Demux/Demux_1X16/waveform.vcd
$date
	Tue Jul  7 18:54:37 2026
$end
$version
	Icarus Verilog
$end
$timescale
	1s
$end
$scope module demux_1X16_tb $end
$var wire 1 ! i9 $end
$var wire 1 " i8 $end
$var wire 1 # i7 $end
$var wire 1 $ i6 $end
$var wire 1 % i5 $end
$var wire 1 & i4 $end
$var wire 1 ' i3 $end
$var wire 1 ( i2 $end
$var wire 1 ) i15 $end
$var wire 1 * i14 $end
$var wire 1 + i13 $end
$var wire 1 , i12 $end
$var wire 1 - i11 $end
$var wire 1 . i10 $end
$var wire 1 / i1 $end
$var wire 1 0 i0 $end
$var reg 1 1 s0 $end
$var reg 1 2 s1 $end
$var reg 1 3 s2 $end
$var reg 1 4 s3 $end
$var reg 1 5 y $end
$scope module dut $end
$var wire 1 1 s0 $end
$var wire 1 2 s1 $end
$var wire 1 3 s2 $end
$var wire 1 4 s3 $end
$var wire 1 5 y $end
$var wire 1 6 y2 $end
$var wire 1 7 y1 $end
$var wire 1 ! i9 $end
$var wire 1 " i8 $end
$var wire 1 # i7 $end
$var wire 1 $ i6 $end
$var wire 1 % i5 $end
$var wire 1 & i4 $end
$var wire 1 ' i3 $end
$var wire 1 ( i2 $end
$var wire 1 ) i15 $end
$var wire 1 * i14 $end
$var wire 1 + i13 $end
$var wire 1 , i12 $end
$var wire 1 - i11 $end
$var wire 1 . i10 $end
$var wire 1 / i1 $end
$var wire 1 0 i0 $end
$scope module dm1 $end
$var wire 1 7 i0 $end
$var wire 1 6 i1 $end
$var wire 1 4 s3 $end
$var wire 1 5 y $end
$upscope $end
$scope module dm2 $end
$var wire 1 0 i0 $end
$var wire 1 / i1 $end
$var wire 1 ( i2 $end
$var wire 1 ' i3 $end
$var wire 1 & i4 $end
$var wire 1 % i5 $end
$var wire 1 $ i6 $end
$var wire 1 # i7 $end
$var wire 1 1 s0 $end
$var wire 1 2 s1 $end
$var wire 1 3 s2 $end
$var wire 1 7 y $end
$upscope $end
$scope module dm3 $end
$var wire 1 " i0 $end
$var wire 1 ! i1 $end
$var wire 1 . i2 $end
$var wire 1 - i3 $end
$var wire 1 , i4 $end
$var wire 1 + i5 $end
$var wire 1 * i6 $end
$var wire 1 ) i7 $end
$var wire 1 1 s0 $end
$var wire 1 2 s1 $end
$var wire 1 3 s2 $end
$var wire 1 6 y $end
$upscope $end
$upscope $end
$upscope $end
$enddefinitions $end
$comment Show the parameter values. $end
$dumpall
$end
#0
$dumpvars
17
06
15
04
03
02
01
10
0/
0.
0-
0,
0+
0*
0)
0(
0'
0&
0%
0$
0#
0"
0!
$end
#10
00
1/
11
#20
1(
0/
01
12
#30
0(
1'
11
#40
1&
0'
01
02
13
#50
0&
1%
11
#60
1$
0%
01
12
#70
0$
1#
11
#80
1"
07
0#
16
01
02
03
14
#90
0"
1!
11
#100
1.
0!
01
12
#110
0.
1-
11
#120
1,
0-
01
02
13
#130
0,
1+
11
#140
1*
0+
01
12
#150
0*
1)
11
