07_Counters/065_BCD_Counter/bcd_counter.v
module bcd_counter(
input clk,rst,
output reg [3:0]q);

always @(posedge clk) begin
    if (rst)
        q <= 4'b000;
    else begin
    	if (q==4'd9)
	    q <= 4'b000;
         else 
            q <= q + 1'b1;

end

end

endmodule

07_Counters/065_BCD_Counter/bcd_counter_tb.v
module bcd_counter_tb();

reg clk;
reg rst;

wire [3:0] q;

bcd_counter dut(.*);

initial clk = 0;
always #10 clk = ~clk;

initial begin

$dumpfile ("waveform.vcd");
$dumpvars (0,bcd_counter_tb);

#10;
rst=1;#30;
rst=0;#250;

$finish;

end

endmodule

07_Counters/065_BCD_Counter/waveform.vcd
$date
	Sat Aug 29 14:10:07 2026
$end
$version
	Icarus Verilog
$end
$timescale
	1s
$end
$scope module bcd_counter_tb $end
$var wire 4 ! q [3:0] $end
$var reg 1 " clk $end
$var reg 1 # rst $end
$scope module dut $end
$var wire 1 " clk $end
$var wire 1 # rst $end
$var reg 4 $ q [3:0] $end
$upscope $end
$upscope $end
$enddefinitions $end
$comment Show the parameter values. $end
$dumpall
$end
#0
$dumpvars
bx $
x#
0"
bx !
$end
#10
b0 !
b0 $
1#
1"
#20
0"
#30
1"
#40
0"
0#
#50
b1 !
b1 $
1"
#60
0"
#70
b10 !
b10 $
1"
#80
0"
#90
b11 !
b11 $
1"
#100
0"
#110
b100 !
b100 $
1"
#120
0"
#130
b101 !
b101 $
1"
#140
0"
#150
b110 !
b110 $
1"
#160
0"
#170
b111 !
b111 $
1"
#180
0"
#190
b1000 !
b1000 $
1"
#200
0"
#210
b1001 !
b1001 $
1"
#220
0"
#230
b0 !
b0 $
1"
#240
0"
#250
b1 !
b1 $
1"
#260
0"
#270
b10 !
b10 $
1"
#280
0"
#290
b11 !
b11 $
1"
