06_Registers/051_8bit_Register/register_8bit.v
module register_8bit(
    input clk, rst,
    input [7:0] d,
    output reg [7:0] q
);

always @(posedge clk) begin

if(rst)
    q <= 7'd0;
else
    q<=d;

end

endmodule

06_Registers/051_8bit_Register/register_8bit_tb.v
module register_8bit_tb();
  reg rst, clk;
  reg [7:0]d;
  wire [7:0]q;

  register_8bit dut (.*);

  always #5 clk=~clk;

  initial begin

   $dumpfile("waveform.vcd");
   $dumpvars(0,register_8bit_tb);
   
    clk=0;
    #10; rst=1; d=8'd0;
    #10; rst=1; d=8'd100;  
    #10; rst=0; d=8'd200;   
    #10; rst=0; d=8'd233;   
    #10; rst=0; d=8'd142;   
    #10; rst=0; d=8'd58;
    #10; rst=0; d=8'd169;   
    #10; rst=0; d=8'd7;   
    #10; rst=0; d=8'd18;
    #10; rst=1; d=8'd95;
    #10; rst=1; d=8'd38;

    #10; $finish;
  end
 endmodule

06_Registers/051_8bit_Register/waveform.vcd
$date
	Wed Aug 26 12:40:04 2026
$end
$version
	Icarus Verilog
$end
$timescale
	1s
$end
$scope module register_8bit_tb $end
$var wire 8 ! q [7:0] $end
$var reg 1 " clk $end
$var reg 8 # d [7:0] $end
$var reg 1 $ rst $end
$scope module dut $end
$var wire 1 " clk $end
$var wire 8 % d [7:0] $end
$var wire 1 $ rst $end
$var reg 8 & q [7:0] $end
$upscope $end
$upscope $end
$enddefinitions $end
$comment Show the parameter values. $end
$dumpall
$end
#0
$dumpvars
bx &
bx %
x$
bx #
0"
bx !
$end
#5
1"
#10
0"
b0 #
b0 %
1$
#15
b0 !
b0 &
1"
#20
0"
b1100100 #
b1100100 %
#25
1"
#30
0"
b11001000 #
b11001000 %
0$
#35
b11001000 !
b11001000 &
1"
#40
0"
b11101001 #
b11101001 %
#45
b11101001 !
b11101001 &
1"
#50
0"
b10001110 #
b10001110 %
#55
b10001110 !
b10001110 &
1"
#60
0"
b111010 #
b111010 %
#65
b111010 !
b111010 &
1"
#70
0"
b10101001 #
b10101001 %
#75
b10101001 !
b10101001 &
1"
#80
0"
b111 #
b111 %
#85
b111 !
b111 &
1"
#90
0"
b10010 #
b10010 %
#95
b10010 !
b10010 &
1"
#100
0"
b1011111 #
b1011111 %
1$
#105
b0 !
b0 &
1"
#110
0"
b100110 #
b100110 %
