07_Counters/059_Down_Counter/down_counter.v
module down_counter(
input clk,rst,
output reg [3:0]count);

always @(posedge clk) begin
    if (rst)
        count <= 4'b0000;
    else
        count <= count - 1'b1;
end

endmodule

07_Counters/059_Down_Counter/down_counter_tb.v
module down_counter_tb();

reg clk;
reg rst;

wire [3:0] count;

down_counter dut(.*);

initial clk = 0;
always #10 clk = ~clk;

initial begin

$dumpfile ("waveform.vcd");
$dumpvars (0,down_counter_tb);

#10;
rst=1;#10;
rst=0;#50;
rst=1;#10;
rst=0;#60;

$finish;

end

endmodule

07_Counters/059_Down_Counter/waveform.vcd
$date
	Fri Aug 28 17:12:28 2026
$end
$version
	Icarus Verilog
$end
$timescale
	1s
$end
$scope module down_counter_tb $end
$var wire 4 ! count [3:0] $end
$var reg 1 " clk $end
$var reg 1 # rst $end
$scope module dut $end
$var wire 1 " clk $end
$var wire 1 # rst $end
$var reg 4 $ count [3:0] $end
$upscope $end
$upscope $end
$enddefinitions $end
$comment Show the parameter values. $end
$dumpall
$end
#0
$dumpvars
bx $
x#
0"
bx !
$end
#10
b0 !
b0 $
1#
1"
#20
0#
0"
#30
b1111 !
b1111 $
1"
#40
0"
#50
b1110 !
b1110 $
1"
#60
0"
#70
b0 !
b0 $
1"
1#
#80
0"
0#
#90
b1111 !
b1111 $
1"
#100
0"
#110
b1110 !
b1110 $
1"
#120
0"
#130
b1101 !
b1101 $
1"
