05_Latches_And_Flipflops/048_DFF_With_Enable/dff_with_enable.v
module dff_with_enable(
input d,clk,rst,en,
output reg q
);

always @(posedge clk) begin
   
    q<=rst?1'b0:(en?d:q);

end

endmodule

05_Latches_And_Flipflops/048_DFF_With_Enable/dff_with_enable_tb.v
module dff_with_enable_tb();
  reg rst, d, clk, en;
  wire q;

  dff_with_enable dut (.*);

  always #5 clk=~clk;

  initial begin

   $dumpfile("waveform.vcd");
   $dumpvars(0,dff_with_enable_tb);
   
    clk=0;
    #10; rst=0;en=0; d=0;
    #10; rst=1; d=0;  
    #10; rst=0; d=1;   
    #10; rst=0;en=1; d=0;   
    #10; rst=1; d=1;   
    #10; rst=0; d=0;
    #10; rst=0; d=1;   
    #10; rst=0; d=0;   
    #10; rst=0; d=1;

    #10; $finish;
  end
 endmodule

05_Latches_And_Flipflops/048_DFF_With_Enable/waveform.vcd
$date
	Wed Aug 26 09:27:12 2026
$end
$version
	Icarus Verilog
$end
$timescale
	1s
$end
$scope module dff_with_enable_tb $end
$var wire 1 ! q $end
$var reg 1 " clk $end
$var reg 1 # d $end
$var reg 1 $ en $end
$var reg 1 % rst $end
$scope module dut $end
$var wire 1 " clk $end
$var wire 1 # d $end
$var wire 1 $ en $end
$var wire 1 % rst $end
$var reg 1 ! q $end
$upscope $end
$upscope $end
$enddefinitions $end
$comment Show the parameter values. $end
$dumpall
$end
#0
$dumpvars
x%
x$
x#
0"
x!
$end
#5
1"
#10
0"
0#
0$
0%
#15
1"
#20
0"
1%
#25
0!
1"
#30
0"
1#
0%
#35
1"
#40
0"
0#
1$
#45
1"
#50
0"
1#
1%
#55
1"
#60
0"
0#
0%
#65
1"
#70
0"
1#
#75
1!
1"
#80
0"
0#
#85
0!
1"
#90
0"
1#
#95
1!
1"
