08_Finite_State_Machines/071_Sequence_Detector_1101/Moore_Sequence_Detector/sequence_detector_1101.v
module sequence_detector_1101 (

    input clk,
    input rst,
    input x,
    output reg y

);					//MOORE OVERLAPPING

parameter S0 = 3'b000,
          S1 = 3'b001,
          S2 = 3'b010,
          S3 = 3'b011,
	  S4 = 3'b100;

reg [2:0] state;
reg [2:0] next_state;


always @(posedge clk or posedge rst) begin

    if (rst)
        state <= S0;
    else
        state <= next_state;

end


always @(*) begin

    case (state)

        S0: begin

            if (x)
                next_state = S1;
            else
                next_state = S0;

        end


        S1: begin

            if (x)
                next_state = S2;
            else
                next_state = S0;

        end


        S2: begin

            if (x)
                next_state = S2;
            else
                next_state = S3;

        end


        S3: begin

	    if (x)
                next_state = S4;
	    else
		next_state = S0;

        end

	S4: begin

	    if (x) 
		next_state = S2;
	    else
		next_state = S0;

	end


        default: begin

            next_state = S0;

        end

    endcase

end


always @(*) begin

    case (state)

        S0: y = 1'b0;
        S1: y = 1'b0;
        S2: y = 1'b0;
	S3: y = 1'b0;
        S4: y = 1'b1;

        default:
            y = 1'b0;

    endcase

end

endmodule

08_Finite_State_Machines/071_Sequence_Detector_1101/Moore_Sequence_Detector/sequence_detector_1101_tb.v
module sequence_detector_1101_tb();

reg clk, rst, x;
wire y;

sequence_detector_1101 dut (.*);

initial clk = 0;
always #5 clk = ~clk;

initial begin

$dumpfile ("waveform.vcd");
$dumpvars (0,sequence_detector_1101_tb);

$monitor ("Time = %0t | rst = %b | x = %b | y = %b|", $time , rst, x, y);

rst = 1;x = 0;#10;
rst = 0;x = 1; #10;
        x = 1; #10;
        x = 1; #10;
	x = 0; #10;
	x = 1; #10;
        x = 1; #10;
        x = 0; #10;
        x = 1; #10;
	x = 1; #30;

$finish;

end

endmodule

08_Finite_State_Machines/071_Sequence_Detector_1101/Moore_Sequence_Detector/waveform.vcd
$date
	Mon Sep  7 09:59:18 2026
$end
$version
	Icarus Verilog
$end
$timescale
	1s
$end
$scope module sequence_detector_1101_tb $end
$var wire 1 ! y $end
$var reg 1 " clk $end
$var reg 1 # rst $end
$var reg 1 $ x $end
$scope module dut $end
$var wire 1 " clk $end
$var wire 1 # rst $end
$var wire 1 $ x $end
$var parameter 3 % S0 $end
$var parameter 3 & S1 $end
$var parameter 3 ' S2 $end
$var parameter 3 ( S3 $end
$var parameter 3 ) S4 $end
$var reg 3 * next_state [2:0] $end
$var reg 3 + state [2:0] $end
$var reg 1 ! y $end
$upscope $end
$upscope $end
$enddefinitions $end
$comment Show the parameter values. $end
$dumpall
b100 )
b11 (
b10 '
b1 &
b0 %
$end
#0
$dumpvars
b0 +
b0 *
0$
1#
0"
0!
$end
#5
1"
#10
b1 *
0"
1$
0#
#15
b10 *
b1 +
1"
#20
0"
#25
b10 +
1"
#30
0"
#35
1"
#40
b11 *
0"
0$
#45
b0 *
b11 +
1"
#50
b100 *
0"
1$
#55
1!
b10 *
b100 +
1"
#60
0"
#65
0!
b10 +
1"
#70
b11 *
0"
0$
#75
b0 *
b11 +
1"
#80
b100 *
0"
1$
#85
1!
b10 *
b100 +
1"
#90
0"
#95
0!
b10 +
1"
