02_Basic_Combinational/009_Full_Adder/full_adder_dataflow.v
module full_adder(
	input a,b,c,
	output sum, carry
);
assign sum= a^b^c;
assign carry=((a&b)|(b&c)|(a&c));
endmodule

02_Basic_Combinational/009_Full_Adder/full_adder_tb.v
`timescale 1ns/1ps

module full_adder_tb;
reg a, b, c;
wire xor_out, and_out1, and_out2, sum, carry;

full_adder uut(
	.a(a),
	.b(b),
	.c(c),
	.sum(sum),
	.carry(carry)
);

initial begin 
	$dumpfile("sim.vcd");
	$dumpvars(0, full_adder_tb);
	$monitor("Time=%0t | a=%b b=%b | sum=%b carry=%b ", $time, a, b, c, sum, carry);

	a=0;b=0;c=0;#10;
	a=0;b=0;c=1;#10;
	a=0;b=1;c=0;#10;
	a=0;b=1;c=1;#10;
	a=1;b=0;c=0;#10;
	a=1;b=0;c=1;#10;
	a=1;b=1;c=0;#10;
	a=1;b=1;c=1;#10;
	$finish;
end
endmodule

02_Basic_Combinational/009_Full_Adder/sim.vcd
$date
	Thu Jun  4 19:03:00 2026
$end
$version
	Icarus Verilog
$end
$timescale
	1ps
$end
$scope module full_adder_tb $end
$var wire 1 ! sum $end
$var wire 1 " carry $end
$var reg 1 # a $end
$var reg 1 $ b $end
$var reg 1 % c $end
$scope module uut $end
$var wire 1 # a $end
$var wire 1 $ b $end
$var wire 1 % c $end
$var reg 1 " carry $end
$var reg 1 ! sum $end
$upscope $end
$upscope $end
$enddefinitions $end
#0
$dumpvars
0%
0$
0#
0"
0!
$end
#10000
1!
1%
#20000
0%
1$
#30000
1"
0!
1%
#40000
0"
1!
0%
0$
1#
#50000
1"
0!
1%
#60000
0%
1$
#70000
1!
1%
