02_Basic_Combinational/009_Full_Adder/full_adder_ifelse.v
module full_adder(
	input  a, b, c,
	output reg sum, carry
);

always @(*) begin
	if ({a, b, c} == 3'b000)begin
		sum = 0; carry = 0;
	end
	else if ({a, b, c} == 3'b001)begin
		sum = 1; carry = 0; 
	end
	else if ({a, b, c} == 3'b010)begin
                 sum = 1; carry = 0;
	end
	else if ({a, b, c} == 3'b011)begin
                 sum = 0; carry = 1;
	 end
	else if ({a, b, c} == 3'b100)begin
                 sum = 1; carry = 0;
	 end
	 else if ({a, b, c} == 3'b101)begin
                sum = 0; carry = 1;
	end
	else if ({a, b, c} == 3'b110)begin
               sum = 0; carry = 1;
       end
       else begin
               sum = 1; carry = 1;
       end
end
endmodule

02_Basic_Combinational/009_Full_Adder/fuh_adder_tb.v
module full_adder_tb();
 reg a,b,c;
 wire sum,carry;
 full_adder f(.a(a),.b(b),.c(c),.sum(sum),.carry(carry));
 initial begin 

    a=0;b=0;c=0;#10 
    a=0;b=0;c=1;#10 
    a=0;b=1;c=0;#10 
    a=0;b=1;c=1;#10 
    a=1;b=0;c=0;#10 
    a=1;b=0;c=1;#10 
    a=1;b=1;c=0;#10 
    a=1;b=1;c=1;
end
initial begin
    $monitor("Time=%0t|a=%b b=%b c=%b|sum=%b carry=%b",$time,a,b,c,sum,carry);
    $dumpfile("sim.vcd");
    $dumpvars(1, full_adder_tb);
end
endmodule

02_Basic_Combinational/009_Full_Adder/sim.vcd
$date
	Fri Jun  5 16:55:41 2026
$end
$version
	Icarus Verilog
$end
$timescale
	1ps
$end
$scope module full_adder_tb $end
$var wire 1 ! sum $end
$var wire 1 " carry $end
$var reg 1 # a $end
$var reg 1 $ b $end
$var reg 1 % c $end
$scope module uut $end
$var wire 1 # a $end
$var wire 1 $ b $end
$var wire 1 % c $end
$var reg 1 " carry $end
$var reg 1 ! sum $end
$upscope $end
$upscope $end
$enddefinitions $end
#0
$dumpvars
0%
0$
0#
0"
0!
$end
#10000
1!
1%
#20000
0%
1$
#30000
1"
0!
1%
#40000
0"
1!
0%
0$
1#
#50000
1"
0!
1%
#60000
0%
1$
#70000
1!
1%
