09_Memory_Basics/080_Dual_Port_RAM/dual_port_ram.v
module dual_port_ram(

input clk_a,
input we_a,
input [2:0] address_a,
input [3:0] data_in_a,
output reg [3:0] data_out_a,


input clk_b,
input we_b,
input [2:0] address_b,
input [3:0] data_in_b,
output reg [3:0] data_out_b

);

reg [3:0] memory [0:7];

always @(posedge clk_a) begin

if(we_a)
memory[address_a] <= data_in_a;
else
data_out_a <= memory [address_a];

end

always @(posedge clk_b) begin

if(we_b)
memory[address_b] <= data_in_b;
else
data_out_b <= memory [address_b];

end

endmodule

09_Memory_Basics/080_Dual_Port_RAM/dual_port_ram_tb.v
module dual_port_ram_tb();

reg clk_a;
reg we_a;
reg [2:0] address_a;
reg [3:0] data_in_a;
wire [3:0] data_out_a;

reg clk_b;
reg we_b;
reg [2:0] address_b;
reg [3:0] data_in_b;
wire [3:0] data_out_b;

dual_port_ram dut(.*);

initial clk_a = 0;
initial clk_b = 0;
always #5 clk_a = ~clk_a;
always #5 clk_b = ~clk_b;

initial begin

$dumpfile ("waveform.vcd");
$dumpvars (0,dual_port_ram_tb);

$monitor("Time=%0t | clk_a = %b | we_a=%b | address_a=%d | data_in_a=%b | data_out_a=%b",
             $time,clk_a,we_a, address_a,data_in_a,data_out_a);

$monitor("Time=%0t | clk_b = %b | we_b=%b | address_b=%d | data_in_b=%b | data_out_b=%b",
             $time,clk_b,we_b, address_b,data_in_b,data_out_b);

we_a = 1; we_b = 1; address_a = 3'd0; data_in_a = 4'd1; #10;
	address_a = 3'd1; data_in_a = 4'd2; #10;
	address_a = 3'd2; data_in_a = 4'd3; #10; data_in_a = 1'dx;
	address_b = 3'd3; data_in_b = 4'd4; #10;
	address_b = 3'd4; data_in_b = 4'd5; #10;
	address_b = 3'd5; data_in_b = 4'd6; #10;data_in_b = 1'dx;

we_a = 0; we_b = 0; address_a = 3'd2; #10;
	address_b = 3'd4; #10;
	address_a = 3'd0; #10;
	address_b = 3'd6; #10;
	address_a = 3'd7; #10;
	address_a = 3'd0; #20;


$finish;

end

endmodule

09_Memory_Basics/080_Dual_Port_RAM/waveform.vcd
$date
	Tue Sep  8 18:39:55 2026
$end
$version
	Icarus Verilog
$end
$timescale
	1s
$end
$scope module dual_port_ram_tb $end
$var wire 4 ! data_out_b [3:0] $end
$var wire 4 " data_out_a [3:0] $end
$var reg 3 # address_a [2:0] $end
$var reg 3 $ address_b [2:0] $end
$var reg 1 % clk_a $end
$var reg 1 & clk_b $end
$var reg 4 ' data_in_a [3:0] $end
$var reg 4 ( data_in_b [3:0] $end
$var reg 1 ) we_a $end
$var reg 1 * we_b $end
$scope module dut $end
$var wire 3 + address_a [2:0] $end
$var wire 3 , address_b [2:0] $end
$var wire 1 % clk_a $end
$var wire 1 & clk_b $end
$var wire 4 - data_in_a [3:0] $end
$var wire 4 . data_in_b [3:0] $end
$var wire 1 ) we_a $end
$var wire 1 * we_b $end
$var reg 4 / data_out_a [3:0] $end
$var reg 4 0 data_out_b [3:0] $end
$upscope $end
$upscope $end
$enddefinitions $end
$comment Show the parameter values. $end
$dumpall
$end
#0
$dumpvars
bx 0
bx /
bx .
b1 -
bx ,
b0 +
1*
1)
bx (
b1 '
0&
0%
bx $
b0 #
bx "
bx !
$end
#5
1&
1%
#10
0&
0%
b10 '
b10 -
b1 #
b1 +
#15
1&
1%
#20
0&
0%
b11 '
b11 -
b10 #
b10 +
#25
1&
1%
#30
0&
0%
b100 (
b100 .
b11 $
b11 ,
b0x '
b0x -
#35
1&
1%
#40
0&
0%
b101 (
b101 .
b100 $
b100 ,
#45
1&
1%
#50
0&
0%
b110 (
b110 .
b101 $
b101 ,
#55
1&
1%
#60
0&
0%
0*
0)
b0x (
b0x .
#65
b110 !
b110 0
b0x "
b0x /
1&
1%
#70
0&
0%
b100 $
b100 ,
#75
b101 !
b101 0
1&
1%
#80
0&
0%
b0 #
b0 +
#85
b1 "
b1 /
1&
1%
#90
0&
0%
b110 $
b110 ,
#95
bx !
bx 0
1&
1%
#100
0&
0%
b111 #
b111 +
#105
bx "
bx /
1&
1%
#110
0&
0%
b0 #
b0 +
#115
b1 "
b1 /
1&
1%
