03_Intermediate_Combinational/019_Priority_Encoder/Priority_Encoder_8X3/priority_encoder_8X3.v
module priority_encoder_8X3(
input [7:0]d,
output reg [2:0]y);

  always @(*) begin 
    casex(d)

        8'b1xxxxxxx: y = 3'd7;
        8'b01xxxxxx: y = 3'd6;
        8'b001xxxxx: y = 3'd5;
        8'b0001xxxx: y = 3'd4;
        8'b00001xxx: y = 3'd3;
        8'b000001xx: y = 3'd2;
        8'b0000001x: y = 3'd1;
        8'b00000001: y = 3'd0;
        default:     y=3'bxxx;

    endcase
  end
endmodule

03_Intermediate_Combinational/019_Priority_Encoder/Priority_Encoder_8X3/priority_encoder_8X3_tb.v
module priority_encoder_8X3_tb();
reg  [7:0]d;
wire [2:0]y;

priority_encoder_8X3 dut(.*);

initial begin

$display("TIME=%0t d=%0b y=%0b",$time,d,y);
$dumpfile("waveform.vcd");
$dumpvars(0,priority_encoder_8X3_tb);

      d= 8'd1;#10;
      d= 8'd2;#10;
      d= 8'd46;#10;
      d= 8'd8;#10;
      d= 8'd16;#10;
      d= 8'd32;#10;
      d= 8'd43;#10;
      d= 8'd128;#10;
      
end

endmodule

03_Intermediate_Combinational/019_Priority_Encoder/Priority_Encoder_8X3/waveform.vcd
$date
	Fri Aug 21 15:33:54 2026
$end
$version
	Icarus Verilog
$end
$timescale
	1s
$end
$scope module priority_encoder_8X3_tb $end
$var wire 3 ! y [2:0] $end
$var reg 8 " d [7:0] $end
$scope module dut $end
$var wire 8 # d [7:0] $end
$var reg 3 $ y [2:0] $end
$upscope $end
$upscope $end
$enddefinitions $end
$comment Show the parameter values. $end
$dumpall
$end
#0
$dumpvars
b0 $
b1 #
b1 "
b0 !
$end
#10
b1 !
b1 $
b10 "
b10 #
#20
b101 !
b101 $
b101110 "
b101110 #
#30
b11 !
b11 $
b1000 "
b1000 #
#40
b100 !
b100 $
b10000 "
b10000 #
#50
b101 !
b101 $
b100000 "
b100000 #
#60
b101011 "
b101011 #
#70
b111 !
b111 $
b10000000 "
b10000000 #
