06_Registers/052_PIPO_Register/pipo_register.v
module pipo_register(
    input clk, rst,
    input [3:0] d,
    output reg [3:0] q
);

always @(posedge clk) begin

if(rst)
    q <= 4'd0;
else
    q<=d;

end

endmodule

06_Registers/052_PIPO_Register/pipo_register_tb.v
module pipo_register_tb();
  reg rst, clk;
  reg [3:0]d;
  wire [3:0]q;

  pipo_register dut (.*);

  always #5 clk=~clk;

  initial begin

   $dumpfile("waveform.vcd");
   $dumpvars(0,pipo_register_tb);
   
    clk=0;
    #10; rst=1; d=4'd0;
    #10; rst=1; d=4'd1;  
    #10; rst=0; d=4'd2;   
    #10; rst=0; d=4'd14;   
    #10; rst=0; d=4'd4;   
    #10; rst=0; d=4'd15;
    #10; rst=0; d=4'd6;   
    #10; rst=0; d=4'd12;   
    #10; rst=0; d=4'd8;
    #10; rst=1; d=4'd9;
    #10; rst=1; d=4'd10;

    #10; $finish;
  end
 endmodule

06_Registers/052_PIPO_Register/waveform.vcd
$date
	Wed Aug 26 15:49:04 2026
$end
$version
	Icarus Verilog
$end
$timescale
	1s
$end
$scope module pipo_register_tb $end
$var wire 4 ! q [3:0] $end
$var reg 1 " clk $end
$var reg 4 # d [3:0] $end
$var reg 1 $ rst $end
$scope module dut $end
$var wire 1 " clk $end
$var wire 4 % d [3:0] $end
$var wire 1 $ rst $end
$var reg 4 & q [3:0] $end
$upscope $end
$upscope $end
$enddefinitions $end
$comment Show the parameter values. $end
$dumpall
$end
#0
$dumpvars
bx &
bx %
x$
bx #
0"
bx !
$end
#5
1"
#10
0"
b0 #
b0 %
1$
#15
b0 !
b0 &
1"
#20
0"
b1 #
b1 %
#25
1"
#30
0"
b10 #
b10 %
0$
#35
b10 !
b10 &
1"
#40
0"
b1110 #
b1110 %
#45
b1110 !
b1110 &
1"
#50
0"
b100 #
b100 %
#55
b100 !
b100 &
1"
#60
0"
b1111 #
b1111 %
#65
b1111 !
b1111 &
1"
#70
0"
b110 #
b110 %
#75
b110 !
b110 &
1"
#80
0"
b1100 #
b1100 %
#85
b1100 !
b1100 &
1"
#90
0"
b1000 #
b1000 %
#95
b1000 !
b1000 &
1"
#100
0"
b1001 #
b1001 %
1$
#105
b0 !
b0 &
1"
#110
0"
b1010 #
b1010 %
