06_Registers/053_PISO_Register/piso_register.v
module piso_register(
    input rst, clk, load,
    input [3:0] d,
    output reg q
);

reg [3:0] shift_reg;

always @(posedge clk or posedge rst) begin

    if (rst) begin
        shift_reg <= 4'b0000;
        q <= 1'b0;
    end

    else if (load) begin
        shift_reg <= d;
    end

    else begin
         q <= shift_reg[3];
         shift_reg <= {shift_reg[2:0], 1'b0};       
    end

end

endmodule

06_Registers/053_PISO_Register/piso_register_tb.v
module piso_register_tb();

reg clk,rst,load;
reg [3:0] d;

wire q;

integer i;

piso_register dut(.*);

initial clk = 0;
always #5 clk = ~ clk;

always @(posedge clk or negedge clk) begin

if (clk)
$display ("Time = %0t: Rising edge", $time);
else
$display ("Time = %0t: Falling edge", $time);

end

initial begin

$dumpfile ("waveform.vcd");
$dumpvars (0,piso_register_tb);

#5

rst = 1;
load = 0;
d = 4'b0000;

#10;
rst = 0;

for (i = 0; i < 16; i = i + 1) begin

d = i;
load = 1;
#10;

load = 0;
#40;

end 

$finish;

end

endmodule

06_Registers/053_PISO_Register/waveform.vcd
$date
	Wed Aug 26 23:55:48 2026
$end
$version
	Icarus Verilog
$end
$timescale
	1s
$end
$scope module piso_register_tb $end
$var wire 1 ! q $end
$var reg 1 " clk $end
$var reg 4 # d [3:0] $end
$var reg 1 $ load $end
$var reg 1 % rst $end
$var integer 32 & i [31:0] $end
$scope module dut $end
$var wire 1 " clk $end
$var wire 4 ' d [3:0] $end
$var wire 1 $ load $end
$var wire 1 % rst $end
$var reg 1 ! q $end
$var reg 4 ( shift_reg [3:0] $end
$upscope $end
$upscope $end
$enddefinitions $end
$comment Show the parameter values. $end
$dumpall
$end
#0
$dumpvars
bx (
bx '
bx &
x%
x$
bx #
0"
x!
$end
#5
0!
b0 (
b0 #
b0 '
0$
1%
1"
#10
0"
#15
1"
1$
b0 &
0%
#20
0"
#25
1"
0$
#30
0"
#35
1"
#40
0"
#45
1"
#50
0"
#55
1"
#60
0"
#65
b1 (
1"
1$
b1 #
b1 '
b1 &
#70
0"
#75
b10 (
1"
0$
#80
0"
#85
b100 (
1"
#90
0"
#95
b1000 (
1"
#100
0"
#105
b0 (
1!
1"
#110
0"
#115
b10 (
1"
1$
b10 #
b10 '
b10 &
#120
0"
#125
b100 (
0!
1"
0$
#130
0"
#135
b1000 (
1"
#140
0"
#145
b0 (
1!
1"
#150
0"
#155
0!
1"
#160
0"
#165
b11 (
1"
1$
b11 #
b11 '
b11 &
#170
0"
#175
b110 (
1"
0$
#180
0"
#185
b1100 (
1"
#190
0"
#195
b1000 (
1!
1"
#200
0"
#205
b0 (
1"
#210
0"
#215
b100 (
1"
1$
b100 #
b100 '
b100 &
#220
0"
#225
b1000 (
0!
1"
0$
#230
0"
#235
b0 (
1!
1"
#240
0"
#245
0!
1"
#250
0"
#255
1"
#260
0"
#265
b101 (
1"
1$
b101 #
b101 '
b101 &
#270
0"
#275
b1010 (
1"
0$
#280
0"
#285
b100 (
1!
1"
#290
0"
#295
b1000 (
0!
1"
#300
0"
#305
b0 (
1!
1"
#310
0"
#315
b110 (
1"
1$
b110 #
b110 '
b110 &
#320
0"
#325
b1100 (
0!
1"
0$
#330
0"
#335
b1000 (
1!
1"
#340
0"
#345
b0 (
1"
#350
0"
#355
0!
1"
#360
0"
#365
b111 (
1"
1$
b111 #
b111 '
b111 &
#370
0"
#375
b1110 (
1"
0$
#380
0"
#385
b1100 (
1!
1"
#390
0"
#395
b1000 (
1"
#400
0"
#405
b0 (
1"
#410
0"
#415
b1000 (
1"
1$
b1000 #
b1000 '
b1000 &
#420
0"
#425
b0 (
1"
0$
#430
0"
#435
0!
1"
#440
0"
#445
1"
#450
0"
#455
1"
#460
0"
#465
b1001 (
1"
1$
b1001 #
b1001 '
b1001 &
#470
0"
#475
b10 (
1!
1"
0$
#480
0"
#485
b100 (
0!
1"
#490
0"
#495
b1000 (
1"
#500
0"
#505
b0 (
1!
1"
#510
0"
#515
b1010 (
1"
1$
b1010 #
b1010 '
b1010 &
#520
0"
#525
b100 (
1"
0$
#530
0"
#535
b1000 (
0!
1"
#540
0"
#545
b0 (
1!
1"
#550
0"
#555
0!
1"
#560
0"
#565
b1011 (
1"
1$
b1011 #
b1011 '
b1011 &
#570
0"
#575
b110 (
1!
1"
0$
#580
0"
#585
b1100 (
0!
1"
#590
0"
#595
b1000 (
1!
1"
#600
0"
#605
b0 (
1"
#610
0"
#615
b1100 (
1"
1$
b1100 #
b1100 '
b1100 &
#620
0"
#625
b1000 (
1"
0$
#630
0"
#635
b0 (
1"
#640
0"
#645
0!
1"
#650
0"
#655
1"
#660
0"
#665
b1101 (
1"
1$
b1101 #
b1101 '
b1101 &
#670
0"
#675
b1010 (
1!
1"
0$
#680
0"
#685
b100 (
1"
#690
0"
#695
b1000 (
0!
1"
#700
0"
#705
b0 (
1!
1"
#710
0"
#715
b1110 (
1"
1$
b1110 #
b1110 '
b1110 &
#720
0"
#725
b1100 (
1"
0$
#730
0"
#735
b1000 (
1"
#740
0"
#745
b0 (
1"
#750
0"
#755
0!
1"
#760
0"
#765
b1111 (
1"
1$
b1111 #
b1111 '
b1111 &
#770
0"
#775
b1110 (
1!
1"
0$
#780
0"
#785
b1100 (
1"
#790
0"
#795
b1000 (
1"
#800
0"
#805
b0 (
1"
#810
0"
#815
0!
1"
b10000 &
