06_Registers/054_SIPO_Register/sipo_register.v
module sipo_register(

    input clk, rst, serial_in,
    output reg [3:0] q

);

always @(posedge clk or posedge rst) begin

if (rst)
q <= 4'b0000;

else 
q <= {q[3:0] , serial_in}; 
//q <= (q << 1) | serial_in;

end

endmodule

06_Registers/054_SIPO_Register/sipo_register_tb.v
module sipo_register_tb();

reg clk;
reg rst;
reg serial_in;

wire [3:0] q;

integer i;

sipo_register dut(.*);

initial clk = 0;
always #5 clk = ~clk;

always @(posedge clk or posedge rst) begin

if (clk)
$display ("Time = %0t: Rising Edge", $time);
else
$display ("Time = %0t: Falling Edge", $time);

end

initial begin

$dumpfile ("waveform.vcd");
$dumpvars (0,sipo_register_tb);

#5 rst = 1;
   serial_in = 0;

   #10 
   rst =0;

for (i = 0; i < 8; i = i + 1) begin

serial_in = i;
#10;

end

$finish;

end

endmodule

06_Registers/054_SIPO_Register/waveform.vcd
$date
	Thu Aug 27 23:41:53 2026
$end
$version
	Icarus Verilog
$end
$timescale
	1s
$end
$scope module sipo_register_tb $end
$var wire 4 ! q [3:0] $end
$var reg 1 " clk $end
$var reg 1 # rst $end
$var reg 1 $ serial_in $end
$var integer 32 % i [31:0] $end
$scope module dut $end
$var wire 1 " clk $end
$var wire 1 # rst $end
$var wire 1 $ serial_in $end
$var reg 4 & q [3:0] $end
$upscope $end
$upscope $end
$enddefinitions $end
$comment Show the parameter values. $end
$dumpall
$end
#0
$dumpvars
bx &
bx %
x$
x#
0"
bx !
$end
#5
b0 !
b0 &
0$
1#
1"
#10
0"
#15
1"
b0 %
0#
#20
0"
#25
b1 !
b1 &
1"
1$
b1 %
#30
0"
#35
b10 !
b10 &
1"
0$
b10 %
#40
0"
#45
b101 !
b101 &
1"
1$
b11 %
#50
0"
#55
b1010 !
b1010 &
1"
0$
b100 %
#60
0"
#65
b101 !
b101 &
1"
1$
b101 %
#70
0"
#75
b1010 !
b1010 &
1"
0$
b110 %
#80
0"
#85
b101 !
b101 &
1"
1$
b111 %
#90
0"
#95
b1011 !
b1011 &
1"
b1000 %
