01_Logic_Gates/001_And_Gate/and_gate_gate.v
module and_gate(
	input a,
	input b,
	output y
);

and(y,a,b);

endmodule

11_Testbenches/095_Basic_Testbench/basic_testbench.v
module and_gate_tb;

reg a;
reg b;

wire y;

// Instantiate DUT
and_gate dut (
    .a(a),
    .b(b),
    .y(y)
);

initial begin

    $dumpfile("waveform.vcd");
    $dumpvars(0, and_gate_tb);

    a = 0;
    b = 0;
    #10;

    a = 0;
    b = 1;
    #10;

    a = 1;
    b = 0;
    #10;

    a = 1;
    b = 1;
    #10;

    a = 0;
    b = 0;
    #10;

    a = 0;
    b = 1;
    #10;

    a = 1;
    b = 0;
    #10;

    a = 1;
    b = 1;
    #10;

    $finish;

end

endmodule

11_Testbenches/095_Basic_Testbench/waveform.vcd
$date
	Sat Sep 12 17:25:07 2026
$end
$version
	Icarus Verilog
$end
$timescale
	1s
$end
$scope module and_gate_tb $end
$var wire 1 ! y $end
$var reg 1 " a $end
$var reg 1 # b $end
$scope module dut $end
$var wire 1 " a $end
$var wire 1 # b $end
$var wire 1 ! y $end
$upscope $end
$upscope $end
$enddefinitions $end
$comment Show the parameter values. $end
$dumpall
$end
#0
$dumpvars
0#
0"
0!
$end
#10
1#
#20
0#
1"
#30
1!
1#
#40
0!
0#
0"
#50
1#
#60
0#
1"
#70
1!
1#
