06_Registers/055_SISO_Register/siso_register.v
module siso_register(

input clk, rst, serial_in,
output serial_out

);

reg [3:0] q;

always @(posedge clk or posedge rst) begin

if(rst) begin
q <= 4'b0000;
end

else begin
q <= { serial_in, q[3:1]};
end

end

assign serial_out = q[3];

endmodule

06_Registers/055_SISO_Register/siso_register_tb.v
module siso_register_tb();

reg clk;
reg rst;
reg serial_in;
wire serial_out;

integer i;

siso_register dut(.*);

initial clk = 0;
always #5 clk = ~clk;

always @(posedge clk or negedge clk) begin

	if (clk)
		$display ("Time = %0t: Rising Edge", $time);
	else
		$display ("Time = %0t: Falling Edge", $time);

end

initial begin

	$dumpfile ("waveform.vcd");
	$dumpvars (0,siso_register_tb);

	#5;
	rst = 1;
	serial_in = 0;

	#5;
	rst = 0;

	for (i = 0; i < 8; i = i +1) begin

		serial_in = i;
		#10;

	end

	$finish;

end

endmodule

06_Registers/055_SISO_Register/waveform.vcd
$date
	Thu Aug 27 23:53:13 2026
$end
$version
	Icarus Verilog
$end
$timescale
	1s
$end
$scope module siso_register_tb $end
$var wire 1 ! serial_out $end
$var reg 1 " clk $end
$var reg 1 # rst $end
$var reg 1 $ serial_in $end
$var integer 32 % i [31:0] $end
$scope module dut $end
$var wire 1 " clk $end
$var wire 1 # rst $end
$var wire 1 $ serial_in $end
$var wire 1 ! serial_out $end
$var reg 4 & q [3:0] $end
$upscope $end
$upscope $end
$enddefinitions $end
$comment Show the parameter values. $end
$dumpall
$end
#0
$dumpvars
bx &
bx %
x$
x#
0"
x!
$end
#5
0!
b0 &
0$
1#
1"
#10
b0 %
0#
0"
#15
1"
#20
0"
1$
b1 %
#25
1!
b1000 &
1"
#30
0"
0$
b10 %
#35
0!
b100 &
1"
#40
0"
1$
b11 %
#45
1!
b1010 &
1"
#50
0"
0$
b100 %
#55
0!
b101 &
1"
#60
0"
1$
b101 %
#65
1!
b1010 &
1"
#70
0"
0$
b110 %
#75
0!
b101 &
1"
#80
0"
1$
b111 %
#85
1!
b1010 &
1"
#90
0"
b1000 %
