11_Testbenches/099_Monitor_Display/design.v
module dff (

input d,
input clk,
output reg q
);

always @(posedge clk) begin

q <= d;

end

endmodule

11_Testbenches/099_Monitor_Display/monitor_display_tb.v
module dff_tb();
  reg d, clk;
  wire q;

  dff dut (.*);
  
  initial clk=0;
  always #5 clk=~clk;

  initial begin

   $dumpfile("waveform.vcd");
   $dumpvars(0,dff_tb);

   $display("T=%0t clk=%b d=%b q=%b", $time, clk, d, q);  //$display statement executes when ever we call them.
   
    clk=0;
    #10; d=0;
    #10; d=0;  
    #10; d=1;   
    #10; d=0;   
    #10; d=1;   
    #10; d=0;
    #10; d=0;   
    #10; d=1;   
    #10; d=0;
    #10; $finish;

    end

    initial begin	//$monitor statement executes whenever the monitoring signal changes (clk or d).

    $monitor("Time=%0t clk=%b d=%b q=%b",
          $time, clk, d, q);

    end

 endmodule

11_Testbenches/099_Monitor_Display/waveform.vcd
$date
	Mon Sep 14 23:41:54 2026
$end
$version
	Icarus Verilog
$end
$timescale
	1s
$end
$scope module dff_tb $end
$var wire 1 ! q $end
$var reg 1 " clk $end
$var reg 1 # d $end
$scope module dut $end
$var wire 1 " clk $end
$var wire 1 # d $end
$var reg 1 ! q $end
$upscope $end
$upscope $end
$enddefinitions $end
$comment Show the parameter values. $end
$dumpall
$end
#0
$dumpvars
x#
0"
x!
$end
#5
1"
#10
0"
0#
#15
0!
1"
#20
0"
#25
1"
#30
0"
1#
#35
1!
1"
#40
0"
0#
#45
0!
1"
#50
0"
1#
#55
1!
1"
#60
0"
0#
#65
0!
1"
#70
0"
#75
1"
#80
0"
1#
#85
1!
1"
#90
0"
0#
#95
0!
1"
