08_Finite_State_Machines/069_Mealy_FSM/mealy_fsm.v
module mealy_fsm(

input clk, rst, x,
output reg y

);

parameter S1 = 2'b00,
          S2 = 2'b01,
          S3 = 2'b10;

reg [1:0] state, next_state;

always @(posedge clk or posedge rst) begin

if (rst)
   state <= S1;
else 
   state <= next_state;

end

always @(*) begin

case (state)

S1: begin

if(x)
next_state = S2;
else
next_state = S1;

end

S2: begin

if(x)
next_state = S3;
else
next_state = S1;

end

S3: begin

if(x)
next_state = S3;
else
next_state = S1;

end

default: next_state = S1;

endcase

end

always @(*) begin
    case (state)

        S1 : y = 1'b0;
        S2 : y = 1'b0;
        S3 : y = x?1'b0:1'b1;

        default : y = 1'b0;

    endcase
end

endmodule

08_Finite_State_Machines/069_Mealy_FSM/mealy_fsm_tb.v
module mealy_fsm_tb();

reg clk, rst, x;
wire y;

mealy_fsm dut (.*);

initial clk = 0;
always #5 clk = ~clk;

initial begin

$dumpfile ("waveform.vcd");
$dumpvars (0,mealy_fsm_tb);

$monitor ("Time = %0t | rst = %b | x = %b | y = %b|", $time , rst, x, y);

rst = 1;x = 0;#10;
rst = 0;x = 1; #10;
        x = 1; #10;
        x = 1; #10;
	x = 0; #10;
	x = 1; #10;
        x = 1; #10;
        x = 0; #10;
        x = 0; #30;

$finish;

end

endmodule

08_Finite_State_Machines/069_Mealy_FSM/waveform.vcd
$date
	Sat Sep  5 11:42:44 2026
$end
$version
	Icarus Verilog
$end
$timescale
	1s
$end
$scope module mealy_fsm_tb $end
$var wire 1 ! y $end
$var reg 1 " clk $end
$var reg 1 # rst $end
$var reg 1 $ x $end
$scope module dut $end
$var wire 1 " clk $end
$var wire 1 # rst $end
$var wire 1 $ x $end
$var parameter 2 % S1 $end
$var parameter 2 & S2 $end
$var parameter 2 ' S3 $end
$var reg 2 ( next_state [1:0] $end
$var reg 2 ) state [1:0] $end
$var reg 1 ! y $end
$upscope $end
$upscope $end
$enddefinitions $end
$comment Show the parameter values. $end
$dumpall
b10 '
b1 &
b0 %
$end
#0
$dumpvars
b0 )
b0 (
0$
1#
0"
0!
$end
#5
1"
#10
b1 (
0"
1$
0#
#15
b10 (
b1 )
1"
#20
0"
#25
b10 )
1"
#30
0"
#35
1"
#40
b0 (
1!
0"
0$
#45
0!
b0 )
1"
#50
b1 (
0"
1$
#55
b10 (
b1 )
1"
#60
0"
#65
b10 )
1"
#70
1!
b0 (
0"
0$
#75
0!
b0 )
1"
