08_Finite_State_Machines/070_Sequence_Detector_101/Moore_Sequence_Detector/Non_Overlapping/sequence_detector_101.v
module sequence_detector_101 (

    input clk,
    input rst,
    input x,
    output reg y

);

parameter S0 = 2'b00,
          S1 = 2'b01,
          S2 = 2'b10,
          S3 = 2'b11;

reg [1:0] state;
reg [1:0] next_state;

always @(posedge clk or posedge rst) begin

    if (rst)
        state <= S0;
    else
        state <= next_state;

end

always @(*) begin

    case (state)


        S0: begin

            if (x)
                next_state = S1;
            else
                next_state = S0;

        end


        S1: begin

            if (x)
                next_state = S1;
            else
                next_state = S2;

        end


        S2: begin

            if (x)
                next_state = S3;
            else
                next_state = S0;

        end


        S3: begin

            next_state = S0;

        end


        default: begin
            next_state = S0;
        end

    endcase

end


always @(*) begin

    case (state)

        S0: y = 1'b0;
        S1: y = 1'b0;
        S2: y = 1'b0;
        S3: y = 1'b1;

        default:
            y = 1'b0;

    endcase

end

endmodule

08_Finite_State_Machines/070_Sequence_Detector_101/Moore_Sequence_Detector/Non_Overlapping/sequence_detector_101_tb.v
module sequence_detector_101_tb();

reg clk, rst, x;
wire y;

sequence_detector_101 dut (.*);

initial clk = 0;
always #5 clk = ~clk;

initial begin

$dumpfile ("waveform.vcd");
$dumpvars (0,sequence_detector_101_tb);

$monitor ("Time = %0t | rst = %b | x = %b | y = %b|", $time , rst, x, y);

rst = 1;x = 0;#10;
rst = 0;x = 1; #10;
        x = 1; #10;
        x = 1; #10;
	x = 0; #10;
	x = 1; #30;
        x = 0; #10;
        x = 1; #10;
        x = 0; #30;

$finish;

end

endmodule

08_Finite_State_Machines/070_Sequence_Detector_101/Moore_Sequence_Detector/Non_Overlapping/waveform.vcd
$date
	Sun Sep  6 23:51:37 2026
$end
$version
	Icarus Verilog
$end
$timescale
	1s
$end
$scope module sequence_detector_101_tb $end
$var wire 1 ! y $end
$var reg 1 " clk $end
$var reg 1 # rst $end
$var reg 1 $ x $end
$scope module dut $end
$var wire 1 " clk $end
$var wire 1 # rst $end
$var wire 1 $ x $end
$var parameter 2 % S0 $end
$var parameter 2 & S1 $end
$var parameter 2 ' S2 $end
$var parameter 2 ( S3 $end
$var reg 2 ) next_state [1:0] $end
$var reg 2 * state [1:0] $end
$var reg 1 ! y $end
$upscope $end
$upscope $end
$enddefinitions $end
$comment Show the parameter values. $end
$dumpall
b11 (
b10 '
b1 &
b0 %
$end
#0
$dumpvars
b0 *
b0 )
0$
1#
0"
0!
$end
#5
1"
#10
b1 )
0"
1$
0#
#15
b1 *
1"
#20
0"
#25
1"
#30
0"
#35
1"
#40
b10 )
0"
0$
#45
b0 )
b10 *
1"
#50
b11 )
0"
1$
#55
1!
b0 )
b11 *
1"
#60
0"
#65
0!
b1 )
b0 *
1"
#70
0"
#75
b1 *
1"
#80
b10 )
0"
0$
#85
b0 )
b10 *
1"
#90
b11 )
0"
1$
#95
1!
b0 )
b11 *
1"
#100
0"
0$
#105
0!
b0 *
1"
