11_Testbenches/100_Self_Checking_Testbench/design.v
module adder (
    input  [3:0] a,
    input  [3:0] b,
    output [4:0] sum
);

assign sum = a - b;

endmodule

11_Testbenches/102_Random_Testbench/random_tb.v
module adder_tb();

reg [3:0] a;
reg [3:0] b;

wire [4:0] sum;

reg  [4:0] expected;

integer i;

adder dut (.*);

initial begin

    $dumpfile("waveform.vcd");
    $dumpvars(0, adder_tb);

    for (i = 0; i < 20; i = i + 1) begin

        a = $random;
        b = $random;

        expected = a + b;

        if (sum == expected)
            $display("PASS: a=%d b=%d expected=%d actual=%d",
                     a, b, expected, sum);
        else
            $display("FAIL: a=%d b=%d expected=%d actual=%d",
                     a, b, expected, sum);

	#10;

    end

    $finish;

end

endmodule

11_Testbenches/102_Random_Testbench/waveform.vcd
$date
	Tue Sep 15 10:21:05 2026
$end
$version
	Icarus Verilog
$end
$timescale
	1s
$end
$scope module adder_tb $end
$var wire 5 ! sum [4:0] $end
$var reg 4 " a [3:0] $end
$var reg 4 # b [3:0] $end
$var reg 5 $ expected [4:0] $end
$var integer 32 % i [31:0] $end
$scope module dut $end
$var wire 4 & a [3:0] $end
$var wire 4 ' b [3:0] $end
$var wire 5 ( sum [4:0] $end
$upscope $end
$upscope $end
$enddefinitions $end
$comment Show the parameter values. $end
$dumpall
$end
#0
$dumpvars
b101 (
b1 '
b100 &
b0 %
b101 $
b1 #
b100 "
b101 !
$end
#10
b1100 $
b11 #
b11 '
b1100 !
b1100 (
b1001 "
b1001 &
b1 %
#20
b11010 $
b1101 #
b1101 '
b11010 !
b11010 (
b1101 "
b1101 &
b10 %
#30
b111 $
b10 #
b10 '
b111 !
b111 (
b101 "
b101 &
b11 %
#40
b1110 $
b1101 #
b1101 '
b1110 !
b1110 (
b1 "
b1 &
b100 %
#50
b10011 $
b10011 !
b10011 (
b110 "
b110 &
b101 %
#60
b11001 $
b1100 #
b1100 '
b11001 !
b11001 (
b1101 "
b1101 &
b110 %
#70
b1111 $
b110 #
b110 '
b1111 !
b1111 (
b1001 "
b1001 &
b111 %
#80
b1010 #
b1010 '
b1111 !
b1111 (
b101 "
b101 &
b1000 %
#90
b1100 $
b1100 !
b1100 (
b111 #
b111 '
b1001 %
#100
b10001 $
b1111 #
b1111 '
b10001 !
b10001 (
b10 "
b10 &
b1010 %
#110
b10000 $
b10000 !
b10000 (
b1110 #
b1110 '
b1011 %
#120
b1101 $
b101 #
b101 '
b1101 !
b1101 (
b1000 "
b1000 &
b1100 %
#130
b11001 $
b1101 #
b1101 '
b11001 !
b11001 (
b1100 "
b1100 &
b1101 %
#140
b10010 $
b101 #
b101 '
b10010 !
b10010 (
b1101 "
b1101 &
b1110 %
#150
b1101 $
b1010 #
b1010 '
b1101 !
b1101 (
b11 "
b11 &
b1111 %
#160
b0 $
b0 #
b0 '
b0 !
b0 (
b0 "
b0 &
b10000 %
#170
b10111 $
b1101 #
b1101 '
b10111 !
b10111 (
b1010 "
b1010 &
b10001 %
#180
b1001 $
b11 #
b11 '
b1001 !
b1001 (
b110 "
b110 &
b10010 %
#190
b10000 $
b10000 !
b10000 (
b1101 "
b1101 &
b10011 %
#200
b10100 %
